fasthtml_cli/__init__.py
fasthtml_cli/cli.py
fasthtml_cli/gallery_fetcher.py
fasthtml_cli/template_builder.py
fasthtml_cli/toml.py
fasthtml_cli/utils.py
fh_cli-0.1.6.dist-info/METADATA
fh_cli-0.1.6.dist-info/WHEEL
fh_cli-0.1.6.dist-info/entry_points.txt
fh_cli-0.1.6.dist-info/licenses/LICENSE
fh_cli-0.1.6.dist-info/RECORD
